<annotation>
	<folder>NHL_Dataset_320x240</folder>
	<filename>320x240-pos-23.jpg</filename>
	<path>/home/cody/GoogleDrive/Data_Sets/NHL_Dataset_320x240/320x240-pos-23.jpg</path>
	<source>
		<database>Unknown</database>
	</source>
	<size>
		<width>320</width>
		<height>216</height>
		<depth>3</depth>
	</size>
	<segmented>0</segmented>
	<object>
		<name>predators</name>
		<pose>Unspecified</pose>
		<truncated>0</truncated>
		<difficult>0</difficult>
		<bndbox>
			<xmin>26</xmin>
			<ymin>25</ymin>
			<xmax>144</xmax>
			<ymax>181</ymax>
		</bndbox>
	</object>
	<object>
		<name>blackhawks</name>
		<pose>Unspecified</pose>
		<truncated>1</truncated>
		<difficult>0</difficult>
		<bndbox>
			<xmin>226</xmin>
			<ymin>86</ymin>
			<xmax>319</xmax>
			<ymax>216</ymax>
		</bndbox>
	</object>
</annotation>
