<annotation>
	<folder>NHL_Dataset_320x240</folder>
	<filename>320x240-pos-32.jpg</filename>
	<path>/home/cody/GoogleDrive/Data_Sets/NHL_Dataset_320x240/320x240-pos-32.jpg</path>
	<source>
		<database>Unknown</database>
	</source>
	<size>
		<width>320</width>
		<height>213</height>
		<depth>3</depth>
	</size>
	<segmented>0</segmented>
	<object>
		<name>blackhawks</name>
		<pose>Unspecified</pose>
		<truncated>0</truncated>
		<difficult>0</difficult>
		<bndbox>
			<xmin>5</xmin>
			<ymin>26</ymin>
			<xmax>104</xmax>
			<ymax>190</ymax>
		</bndbox>
	</object>
	<object>
		<name>blackhawks</name>
		<pose>Unspecified</pose>
		<truncated>0</truncated>
		<difficult>0</difficult>
		<bndbox>
			<xmin>92</xmin>
			<ymin>11</ymin>
			<xmax>157</xmax>
			<ymax>143</ymax>
		</bndbox>
	</object>
	<object>
		<name>blackhawks</name>
		<pose>Unspecified</pose>
		<truncated>0</truncated>
		<difficult>0</difficult>
		<bndbox>
			<xmin>244</xmin>
			<ymin>42</ymin>
			<xmax>287</xmax>
			<ymax>161</ymax>
		</bndbox>
	</object>
	<object>
		<name>blackhawks</name>
		<pose>Unspecified</pose>
		<truncated>1</truncated>
		<difficult>0</difficult>
		<bndbox>
			<xmin>275</xmin>
			<ymin>151</ymin>
			<xmax>320</xmax>
			<ymax>211</ymax>
		</bndbox>
	</object>
</annotation>
